platemapping/__init__.py
platemapping/plate_map.py
platemapping-2.0.0.dist-info/LICENSE
platemapping-2.0.0.dist-info/METADATA
platemapping-2.0.0.dist-info/WHEEL
platemapping-2.0.0.dist-info/top_level.txt
platemapping-2.0.0.dist-info/RECORD
