Metadata-Version: 2.1
Name: platemapping
Version: 2.0.0
Summary: Plate map uploading, processing & visualisaion
Home-page: https://github.com/lawrencecollins/platemapping
Author: Stuart Warriner, Lawrence Collins, Mariusz Las
Author-email: s.l.warriner@leeds.ac.uk, lawrencejordancollins@gmail.com, cm18mel@leeds.ac.uk
License: UNKNOWN
Platform: UNKNOWN
Classifier: Programming Language :: Python :: 3
Classifier: License :: OSI Approved :: MIT License
Classifier: Operating System :: OS Independent
Requires-Python: >=3.6
